llama_index/readers/graphdb_cypher/__init__.py
llama_index/readers/graphdb_cypher/base.py
llama_index_readers_graphdb_cypher-0.4.1.dist-info/METADATA
llama_index_readers_graphdb_cypher-0.4.1.dist-info/WHEEL
llama_index_readers_graphdb_cypher-0.4.1.dist-info/licenses/LICENSE
llama_index_readers_graphdb_cypher-0.4.1.dist-info/RECORD
