Metadata-Version: 2.4
Name: llama-index-readers-graphdb-cypher
Version: 0.4.1
Summary: llama-index readers graphdb_cypher integration
Author-email: Your Name <you@example.com>
Maintainer: jexp
License-Expression: MIT
License-File: LICENSE
Keywords: cypher,graph,neo4j
Requires-Python: <4.0,>=3.9
Requires-Dist: llama-index-core<0.15,>=0.13.0
Requires-Dist: neo4j<6,>=5.16.0
